{
  "code": 0,
  "msg": "",
  "count": 1000,
  "data":[
  {
    "岗位名称": "图书馆图书整理",
    "所属部门 / 用工单位": "图书馆",
    "岗位类型": "校内",
    "工作地点": "学校图书馆三楼",
    "工作时间": "周一至周五 9:00-17:00",
    "联系人及电话": "李老师 13800138001",
    "报名截止日期": "10/15/25",
    "岗位状态": "报名中",
    "需求备注": "需熟悉图书分类，有耐心",
    "总需要人数": "20"
  },
  {
    "岗位名称": "校园快递分拣",
    "所属部门 / 用工单位": "校外合作快递点",
    "岗位类型": "校外",
    "工作地点": "学校东门快递站",
    "工作时间": "周一至周日 14:00-18:00",
    "联系人及电话": "王经理 13900139001",
    "报名截止日期": "10/20/25",
    "岗位状态": "已发布",
    "需求备注": "能吃苦耐劳，手脚麻利",
    "总需要人数": "10"
  },
  {
    "岗位名称": "计算机机房维护",
    "所属部门 / 用工单位": "信息中心",
    "岗位类型": "校内",
    "工作地点": "实验楼 B 栋 501",
    "工作时间": "周二、周四 18:00-21:00",
    "联系人及电话": "张工 13700137001",
    "报名截止日期": "10/10/25",
    "岗位状态": "已截止",
    "需求备注": "需具备计算机基础，会简单故障排查",
    "总需要人数": "10"
  },
  {
    "岗位名称": "食堂菜品打餐",
    "所属部门 / 用工单位": "学校食堂",
    "岗位类型": "校内",
    "工作地点": "学校一食堂",
    "工作时间": "工作日 11:00-13:00、17:00-19:00",
    "联系人及电话": "刘师傅 13600136001",
    "报名截止日期": "10/25/25",
    "岗位状态": "报名中",
    "需求备注": "需注意卫生，动作迅速",
    "总需要人数": "10"
  },
  {
    "岗位名称": "校园文创设计",
    "所属部门 / 用工单位": "校团委",
    "岗位类型": "校内",
    "工作地点": "团委办公室",
    "工作时间": "灵活时段，每周至少 10 小时",
    "联系人及电话": "陈老师 13500135001",
    "报名截止日期": "10/30/25",
    "岗位状态": "已发布",
    "需求备注": "有设计相关经验或技能优先",
    "总需要人数": "10"
  },
  {
    "岗位名称": "校园绿植养护",
    "所属部门 / 用工单位": "后勤管理处",
    "岗位类型": "校内",
    "工作地点": "学校花园区域",
    "工作时间": "周一至周五 8:30-11:30",
    "联系人及电话": "赵师傅 13400134001",
    "报名截止日期": "11/5/25",
    "岗位状态": "报名中",
    "需求备注": "喜欢植物，了解基本养护知识",
    "总需要人数": "10"
  },
  {
    "岗位名称": "校外教育机构助教",
    "所属部门 / 用工单位": "XX 教育培训机构",
    "岗位类型": "校外",
    "工作地点": "市区 XX 大厦 15 层",
    "工作时间": "周六、周日 9:00-16:00",
    "联系人及电话": "杨老师 13300133001",
    "报名截止日期": "11/10/25",
    "岗位状态": "已发布",
    "需求备注": "师范类专业或有教学经验优先",
    "总需要人数": "10"
  },
  {
    "岗位名称": "校史馆讲解",
    "所属部门 / 用工单位": "学校宣传部",
    "岗位类型": "校内",
    "工作地点": "校史馆",
    "工作时间": "周末及节假日 10:00-16:00",
    "联系人及电话": "周老师 13200132001",
    "报名截止日期": "10/5/25",
    "岗位状态": "已截止",
    "需求备注": "形象好，表达能力强，熟悉校史",
    "总需要人数": "10"
  },
  {
    "岗位名称": "校园新媒体运营",
    "所属部门 / 用工单位": "学校新媒体中心",
    "岗位类型": "校内",
    "工作地点": "行政楼 402 室",
    "工作时间": "灵活时段，每周至少 12 小时",
    "联系人及电话": "吴同学 13100131001",
    "报名截止日期": "11/15/25",
    "岗位状态": "报名中",
    "需求备注": "会图文编辑、视频剪辑等技能",
    "总需要人数": "10"
  },
  {
    "岗位名称": "校外商场导购",
    "所属部门 / 用工单位": "XX 商场",
    "岗位类型": "校外",
    "工作地点": "市区 XX 商场内",
    "工作时间": "周末 10:00-20:00（排班制）",
    "联系人及电话": "郑经理 13000130001",
    "报名截止日期": "11/20/25",
    "岗位状态": "已发布",
    "需求备注": "性格开朗，有销售热情",
    "总需要人数": "10"
  }
]
}